collibra_core/__init__.py
collibra_core/api_client.py
collibra_core/configuration.py
collibra_core/rest.py
collibra_core/api/__init__.py
collibra_core/api/activities_api.py
collibra_core/api/application_api.py
collibra_core/api/asset_types_api.py
collibra_core/api/assets_api.py
collibra_core/api/assignments_api.py
collibra_core/api/attachments_api.py
collibra_core/api/attribute_types_api.py
collibra_core/api/attributes_api.py
collibra_core/api/authentication__sessions_api.py
collibra_core/api/comments_api.py
collibra_core/api/communities_api.py
collibra_core/api/complex_relation_types_api.py
collibra_core/api/complex_relations_api.py
collibra_core/api/data_quality_rules_api.py
collibra_core/api/diagram_pictures_api.py
collibra_core/api/domain_types_api.py
collibra_core/api/domains_api.py
collibra_core/api/files_api.py
collibra_core/api/issues_api.py
collibra_core/api/jdbc_driver_api.py
collibra_core/api/jobs_api.py
collibra_core/api/mappings_api.py
collibra_core/api/navigation_statistics_api.py
collibra_core/api/output_module_api.py
collibra_core/api/ratings_api.py
collibra_core/api/relation_types_api.py
collibra_core/api/relations_api.py
collibra_core/api/reporting_api.py
collibra_core/api/responsibilities_api.py
collibra_core/api/roles_api.py
collibra_core/api/saml_api.py
collibra_core/api/scopes_api.py
collibra_core/api/statuses_api.py
collibra_core/api/tags_api.py
collibra_core/api/user_groups_api.py
collibra_core/api/users_api.py
collibra_core/api/validation_api.py
collibra_core/api/view_permissions_api.py
collibra_core/api/workflow_definitions_api.py
collibra_core/api/workflow_instances_api.py
collibra_core/api/workflow_tasks_api.py
collibra_core/models/__init__.py
collibra_core/models/activity_impl.py
collibra_core/models/activity_paged_response.py
collibra_core/models/add_asset_request.py
collibra_core/models/add_asset_tags_request.py
collibra_core/models/add_asset_type_assignment_rule_request.py
collibra_core/models/add_asset_type_request.py
collibra_core_200-2.0.6.dist-info/METADATA
collibra_core_200-2.0.6.dist-info/WHEEL
collibra_core_200-2.0.6.dist-info/top_level.txt
collibra_core_200-2.0.6.dist-info/RECORD
