Metadata-Version: 2.1
Name: collibra-core-200
Version: 2.0.6
Summary: Collibra Data Governance Center Core API
Home-page: 
Author-email: 
Keywords: Swagger,Collibra Data Governance Center Core API
Requires-Dist: urllib3>=1.15
Requires-Dist: six>=1.10
Requires-Dist: certifi
Requires-Dist: python-dateutil
